Metadata-Version: 1.0
Name: table2excel
Version: 0.0.1
Summary: Dump Table (List in List) to an excel file
Home-page: https://github.com/theatoken/table2excel
Author: Alexander.Li
Author-email: superpowerlee@gmail.com
License: MIT
Platform: UNKNOWN
